Workbook

Sheet Rezumat
A1: Raport pentru contabilitate - T3 2026 (iulie-septembrie)
A2: Magazin fictiv de electronice si accesorii. Toate sumele in lei, fara TVA.
A4: Contul de profit si pierdere | B4: Iulie | C4: August | D4: Septembrie | E4: Total T3
A5: Venituri din vanzari | B5: =SUMIFS(Vanzari!$J:$J,Vanzari!$A:$A,"2026-07") -> 149435.57 | C5: =SUMIFS(Vanzari!$J:$J,Vanzari!$A:$A,"2026-08") -> 124418.19 | D5: =SUMIFS(Vanzari!$J:$J,Vanzari!$A:$A,"2026-09") -> 152654.62 | E5: =SUM(B5:D5) -> 426508.38
A6: Costul marfii vandute | B6: =SUMIFS(Vanzari!$M:$M,Vanzari!$A:$A,"2026-07") -> 84135 | C6: =SUMIFS(Vanzari!$M:$M,Vanzari!$A:$A,"2026-08") -> 69320 | D6: =SUMIFS(Vanzari!$M:$M,Vanzari!$A:$A,"2026-09") -> 84270 | E6: =SUM(B6:D6) -> 237725
A7: Marja bruta | B7: =B5-B6 -> 65300.57 | C7: =C5-C6 -> 55098.19 | D7: =D5-D6 -> 68384.62 | E7: =SUM(B7:D7) -> 188783.38
A8: Marja bruta % | B8: =IF(B5=0,0,B7/B5) -> 0.43698144 | C8: =IF(C5=0,0,C7/C5) -> 0.44284674 | D8: =IF(D5=0,0,D7/D5) -> 0.44796954 | E8: =IF(E5=0,0,E7/E5) -> 0.44262525
A9: Cheltuieli operationale
A10: Chirie | B10: =SUMIFS(Cheltuieli!$F:$F,Cheltuieli!$A:$A,"2026-07",Cheltuieli!$C:$C,"Chirie") -> 6500 | C10: =SUMIFS(Cheltuieli!$F:$F,Cheltuieli!$A:$A,"2026-08",Cheltuieli!$C:$C,"Chirie") -> 6500 | D10: =SUMIFS(Cheltuieli!$F:$F,Cheltuieli!$A:$A,"2026-09",Cheltuieli!$C:$C,"Chirie") -> 6500 | E10: =SUM(B10:D10) -> 19500
A11: Utilitati | B11: =SUMIFS(Cheltuieli!$F:$F,Cheltuieli!$A:$A,"2026-07",Cheltuieli!$C:$C,"Utilitati") -> 1935.3 | C11: =SUMIFS(Cheltuieli!$F:$F,Cheltuieli!$A:$A,"2026-08",Cheltuieli!$C:$C,"Utilitati") -> 2061.55 | D11: =SUMIFS(Cheltuieli!$F:$F,Cheltuieli!$A:$A,"2026-09",Cheltuieli!$C:$C,"Utilitati") -> 1885.35 | E11: =SUM(B11:D11) -> 5882.2
A12: Contabilitate | B12: =SUMIFS(Cheltuieli!$F:$F,Cheltuieli!$A:$A,"2026-07",Cheltuieli!$C:$C,"Contabilitate") -> 900 | C12: =SUMIFS(Cheltuieli!$F:$F,Cheltuieli!$A:$A,"2026-08",Cheltuieli!$C:$C,"Contabilitate") -> 900 | D12: =SUMIFS(Cheltuieli!$F:$F,Cheltuieli!$A:$A,"2026-09",Cheltuieli!$C:$C,"Contabilitate") -> 900 | E12: =SUM(B12:D12) -> 2700
A13: Software | B13: =SUMIFS(Cheltuieli!$F:$F,Cheltuieli!$A:$A,"2026-07",Cheltuieli!$C:$C,"Software") -> 420 | C13: =SUMIFS(Cheltuieli!$F:$F,Cheltuieli!$A:$A,"2026-08",Cheltuieli!$C:$C,"Software") -> 420 | D13: =SUMIFS(Cheltuieli!$F:$F,Cheltuieli!$A:$A,"2026-09",Cheltuieli!$C:$C,"Software") -> 420 | E13: =SUM(B13:D13) -> 1260
A14: Marketing | B14: =SUMIFS(Cheltuieli!$F:$F,Cheltuieli!$A:$A,"2026-07",Cheltuieli!$C:$C,"Marketing") -> 2100 | C14: =SUMIFS(Cheltuieli!$F:$F,Cheltuieli!$A:$A,"2026-08",Cheltuieli!$C:$C,"Marketing") -> 2650 | D14: =SUMIFS(Cheltuieli!$F:$F,Cheltuieli!$A:$A,"2026-09",Cheltuieli!$C:$C,"Marketing") -> 2300 | E14: =SUM(B14:D14) -> 7050
A15: Transport | B15: =SUMIFS(Cheltuieli!$F:$F,Cheltuieli!$A:$A,"2026-07",Cheltuieli!$C:$C,"Transport") -> 1045.2 | C15: =SUMIFS(Cheltuieli!$F:$F,Cheltuieli!$A:$A,"2026-08",Cheltuieli!$C:$C,"Transport") -> 985.7 | D15: =SUMIFS(Cheltuieli!$F:$F,Cheltuieli!$A:$A,"2026-09",Cheltuieli!$C:$C,"Transport") -> 1120.5 | E15: =SUM(B15:D15) -> 3151.4
A16: Consumabile | B16: =SUMIFS(Cheltuieli!$F:$F,Cheltuieli!$A:$A,"2026-07",Cheltuieli!$C:$C,"Consumabile") -> 340.5 | C16: =SUMIFS(Cheltuieli!$F:$F,Cheltuieli!$A:$A,"2026-08",Cheltuieli!$C:$C,"Consumabile") -> 310.25 | D16: =SUMIFS(Cheltuieli!$F:$F,Cheltuieli!$A:$A,"2026-09",Cheltuieli!$C:$C,"Consumabile") -> 365.8 | E16: =SUM(B16:D16) -> 1016.55
A17: Mentenanta | B17: =SUMIFS(Cheltuieli!$F:$F,Cheltuieli!$A:$A,"2026-07",Cheltuieli!$C:$C,"Mentenanta") -> 620 | C17: =SUMIFS(Cheltuieli!$F:$F,Cheltuieli!$A:$A,"2026-08",Cheltuieli!$C:$C,"Mentenanta") -> 0 | D17: =SUMIFS(Cheltuieli!$F:$F,Cheltuieli!$A:$A,"2026-09",Cheltuieli!$C:$C,"Mentenanta") -> 450 | E17: =SUM(B17:D17) -> 1070
A18: Banca | B18: =SUMIFS(Cheltuieli!$F:$F,Cheltuieli!$A:$A,"2026-07",Cheltuieli!$C:$C,"Banca") -> 58.9 | C18: =SUMIFS(Cheltuieli!$F:$F,Cheltuieli!$A:$A,"2026-08",Cheltuieli!$C:$C,"Banca") -> 55.4 | D18: =SUMIFS(Cheltuieli!$F:$F,Cheltuieli!$A:$A,"2026-09",Cheltuieli!$C:$C,"Banca") -> 62.3 | E18: =SUM(B18:D18) -> 176.6
A19: Echipamente IT | B19: =SUMIFS(Cheltuieli!$F:$F,Cheltuieli!$A:$A,"2026-07",Cheltuieli!$C:$C,"Echipamente IT") -> 0 | C19: =SUMIFS(Cheltuieli!$F:$F,Cheltuieli!$A:$A,"2026-08",Cheltuieli!$C:$C,"Echipamente IT") -> 780 | D19: =SUMIFS(Cheltuieli!$F:$F,Cheltuieli!$A:$A,"2026-09",Cheltuieli!$C:$C,"Echipamente IT") -> 0 | E19: =SUM(B19:D19) -> 780
A20: Salarii brute | B20: =SUMIFS(Salarii!$E:$E,Salarii!$A:$A,"2026-07") -> 34525 | C20: =SUMIFS(Salarii!$E:$E,Salarii!$A:$A,"2026-08") -> 34525 | D20: =SUMIFS(Salarii!$E:$E,Salarii!$A:$A,"2026-09") -> 34525 | E20: =SUM(B20:D20) -> 103575
A21: CAM (contributie angajator) | B21: =SUMIFS(Salarii!$K:$K,Salarii!$A:$A,"2026-07") -> 778 | C21: =SUMIFS(Salarii!$K:$K,Salarii!$A:$A,"2026-08") -> 778 | D21: =SUMIFS(Salarii!$K:$K,Salarii!$A:$A,"2026-09") -> 778 | E21: =SUM(B21:D21) -> 2334
A22: Total cheltuieli operationale | B22: =SUM(B10:B21) -> 49222.9 | C22: =SUM(C10:C21) -> 49965.9 | D22: =SUM(D10:D21) -> 49306.95 | E22: =SUM(B22:D22) -> 148495.75
A24: Profit inainte de impozit | B24: =B7-B22 -> 16077.67 | C24: =C7-C22 -> 5132.29 | D24: =D7-D22 -> 19077.67 | E24: =SUM(B24:D24) -> 40287.63
A25: Impozit pe profit estimat (16%) | B25: =MAX(0,ROUND(B24*Ipoteze!$B$10,0)) -> 2572 | C25: =MAX(0,ROUND(C24*Ipoteze!$B$10,0)) -> 821 | D25: =MAX(0,ROUND(D24*Ipoteze!$B$10,0)) -> 3052 | E25: =SUM(B25:D25) -> 6445
A26: Profit net estimat | B26: =B24-B25 -> 13505.67 | C26: =C24-C25 -> 4311.29 | D26: =D24-D25 -> 16025.67 | E26: =SUM(B26:D26) -> 33842.63
A27: Marja neta % | B27: =IF(B5=0,0,B26/B5) -> 0.09037788 | C27: =IF(C5=0,0,C26/C5) -> 0.034651605 | D27: =IF(D5=0,0,D26/D5) -> 0.10497992 | E27: =IF(E5=0,0,E26/E5) -> 0.079348101
A29: Indicatori de bilant si de control
A30: Indicator | B30: Iulie | C30: August | D30: Septembrie | E30: Total T3
A31: Achizitii marfa (fara TVA) | B31: =SUMIFS(Achizitii!$I:$I,Achizitii!$A:$A,"2026-07") -> 92900 | C31: =SUMIFS(Achizitii!$I:$I,Achizitii!$A:$A,"2026-08") -> 59240 | D31: =SUMIFS(Achizitii!$I:$I,Achizitii!$A:$A,"2026-09") -> 80955 | E31: =SUM(B31:D31) -> 233095
A32: Valoare stoc la final de luna | B32: =SUMIFS(Stocuri!$I:$I,Stocuri!$A:$A,"2026-07") -> 43557 | C32: =SUMIFS(Stocuri!$I:$I,Stocuri!$A:$A,"2026-08") -> 33477 | D32: =SUMIFS(Stocuri!$I:$I,Stocuri!$A:$A,"2026-09") -> 30162 | E32: =D32 -> 30162
A33: TVA de plata | B33: =TVA!B9 -> 8981.59 | C33: =TVA!C9 -> 10642.04 | D33: =TVA!D9 -> 12150.3 | E33: =SUM(B33:D33) -> 31773.93
A34: Salarii nete de plata | B34: =SUMIFS(Salarii!$J:$J,Salarii!$A:$A,"2026-07") -> 20196 | C34: =SUMIFS(Salarii!$J:$J,Salarii!$A:$A,"2026-08") -> 20196 | D34: =SUMIFS(Salarii!$J:$J,Salarii!$A:$A,"2026-09") -> 20196 | E34: =SUM(B34:D34) -> 60588
A35: Contributii si impozit salarii de plata (CAS+CASS+impozit+CAM) | B35: =SUMIFS(Salarii!$F:$F,Salarii!$A:$A,"2026-07")+SUMIFS(Salarii!$G:$G,Salarii!$A:$A,"2026-07")+SUMIFS(Salarii!$I:$I,Salarii!$A:$A,"2026-07")+SUMIFS(Salarii!$K:$K,Salarii!$A:$A,"2026-07") -> 15107 | C35: =SUMIFS(Salarii!$F:$F,Salarii!$A:$A,"2026-08")+SUMIFS(Salarii!$G:$G,Salarii!$A:$A,"2026-08")+SUMIFS(Salarii!$I:$I,Salarii!$A:$A,"2026-08")+SUMIFS(Salarii!$K:$K,Salarii!$A:$A,"2026-08") -> 15107 | D35: =SUMIFS(Salarii!$F:$F,Salarii!$A:$A,"2026-09")+SUMIFS(Salarii!$G:$G,Salarii!$A:$A,"2026-09")+SUMIFS(Salarii!$I:$I,Salarii!$A:$A,"2026-09")+SUMIFS(Salarii!$K:$K,Salarii!$A:$A,"2026-09") -> 15107 | E35: =SUM(B35:D35) -> 45321
A36: Creante clienti neincasate la 30.09 (cu TVA) | E36: =Clienti!J10 -> 141646.71
A37: Numar facturi emise | B37: =COUNTIFS(Vanzari!$A:$A,"2026-07") -> 119 | C37: =COUNTIFS(Vanzari!$A:$A,"2026-08") -> 118 | D37: =COUNTIFS(Vanzari!$A:$A,"2026-09") -> 114 | E37: =SUM(B37:D37) -> 351
A39: Note: parametrii (cote TVA, contributii, impozit) sunt in foaia Ipoteze. Salariile nu includ deducerea personala (simplificare). Impozitul pe profit e o estimare, nu calculul final.

Sheet Ipoteze
A1: Ipoteze si parametri
A3: Parametru | B3: Valoare | C3: Nota
A4: Cota TVA standard | B4: 0.21 | C4: Cota standard TVA in Romania de la 01.08.2025
A5: Cota TVA apa si canalizare | B5: 0.11 | C5: Cota redusa pentru apa, de la 01.08.2025
A6: CAS (pensie) - angajat | B6: 0.25 | C6: Retinut din salariul brut
A7: CASS (sanatate) - angajat | B7: 0.1 | C7: Retinut din salariul brut
A8: Impozit pe venit salarii | B8: 0.1 | C8: Aplicat pe brut - CAS - CASS; deducerea personala NU e inclusa (simplificare didactica)
A9: CAM - angajator | B9: 0.0225 | C9: Contributia asiguratorie pentru munca, platita de firma
A10: Impozit pe profit (estimat) | B10: 0.16 | C10: Firma depaseste plafonul de microintreprindere; estimare trimestriala
A11: Data de referinta creante | B11: 46295 | C11: Facturile cu scadenta dupa aceasta data sunt considerate neincasate
A13: Celulele galbene cu text albastru sunt date de intrare: daca le modifici, tot raportul se recalculeaza.
A14: Date sursa: fisierele CSV ale magazinului (vanzari, cheltuieli, achizitii, inventar, stat de plata) pentru iulie-septembrie 2026. Firma si datele sunt fictive.

Sheet Vanzari
A1: Luna | B1: Data | C1: Nr factura | D1: Produs | E1: Categorie | F1: Cantitate | G1: Pret unitar fara TVA | H1: Cost achizitie unitar | I1: Client | J1: Valoare fara TVA | K1: TVA | L1: Total cu TVA | M1: Cost marfa vanduta | N1: Termen plata (zile) | O1: Scadenta | P1: Status la 30.09
A2: 2026-07 | B2: 46204 | C2: NB-0764 | D2: Hub USB-C 7in1 | E2: Accesorii | F2: 9 | G2: 169 | H2: 85 | I2: Beta Studio SRL | J2: =F2*G2 -> 1521 | K2: =ROUND(J2*Ipoteze!$B$4,2) -> 319.41 | L2: =J2+K2 -> 1840.41 | M2: =F2*H2 -> 765 | N2: =INDEX(Clienti!$E:$E,MATCH(I2,Clienti!$A:$A,0)) -> 15 | O2: =B2+N2 -> 46219 | P2: =IF(O2>Ipoteze!$B$11,"Neincasat","Incasat") -> Incasat
A3: 2026-07 | B3: 46204 | C3: NB-0765 | D3: Mouse wireless M200 | E3: Periferice | F3: 1 | G3: 79.99 | H3: 45 | I3: Persoana fizica | J3: =F3*G3 -> 79.99 | K3: =ROUND(J3*Ipoteze!$B$4,2) -> 16.8 | L3: =J3+K3 -> 96.79 | M3: =F3*H3 -> 45 | N3: =INDEX(Clienti!$E:$E,MATCH(I3,Clienti!$A:$A,0)) -> 0 | O3: =B3+N3 -> 46204 | P3: =IF(O3>Ipoteze!$B$11,"Neincasat","Incasat") -> Incasat
A4: 2026-07 | B4: 46204 | C4: NB-0766 | D4: Cablu HDMI 2.1 3m | E4: Cabluri | F4: 12 | G4: 54.9 | H4: 22 | I4: Beta Studio SRL | J4: =F4*G4 -> 658.8 | K4: =ROUND(J4*Ipoteze!$B$4,2) -> 138.35 | L4: =J4+K4 -> 797.15 | M4: =F4*H4 -> 264 | N4: =INDEX(Clienti!$E:$E,MATCH(I4,Clienti!$A:$A,0)) -> 15 | O4: =B4+N4 -> 46219 | P4: =IF(O4>Ipoteze!$B$11,"Neincasat","Incasat") -> Incasat
A5: 2026-07 | B5: 46205 | C5: NB-0767 | D5: Cablu USB-C 2m | E5: Cabluri | F5: 1 | G5: 29.99 | H5: 9 | I5: Persoana fizica | J5: =F5*G5 -> 29.99 | K5: =ROUND(J5*Ipoteze!$B$4,2) -> 6.3 | L5: =J5+K5 -> 36.29 | M5: =F5*H5 -> 9 | N5: =INDEX(Clienti!$E:$E,MATCH(I5,Clienti!$A:$A,0)) -> 0 | O5: =B5+N5 -> 46205 | P5: =IF(O5>Ipoteze!$B$11,"Neincasat","Incasat") -> Incasat
A6: 2026-07 | B6: 46205 | C6: NB-0768 | D6: Suport laptop aluminiu | E6: Accesorii | F6: 2 | G6: 99 | H6: 48 | I6: Online - eMag | J6: =F6*G6 -> 198 | K6: =ROUND(J6*Ipoteze!$B$4,2) -> 41.58 | L6: =J6+K6 -> 239.58 | M6: =F6*H6 -> 96 | N6: =INDEX(Clienti!$E:$E,MATCH(I6,Clienti!$A:$A,0)) -> 14 | O6: =B6+N6 -> 46219 | P6: =IF(O6>Ipoteze!$B$11,"Neincasat","Incasat") -> Incasat
A7: 2026-07 | B7: 46205 | C7: NB-0769 | D7: Mousepad XL | E7: Accesorii | F7: 9 | G7: 49.9 | H7: 19 | I7: Gamma Logistic SRL | J7: =F7*G7 -> 449.1 | K7: =ROUND(J7*Ipoteze!$B$4,2) -> 94.31 | L7: =J7+K7 -> 543.41 | M7: =F7*H7 -> 171 | N7: =INDEX(Clienti!$E:$E,MATCH(I7,Clienti!$A:$A,0)) -> 30 | O7: =B7+N7 -> 46235 | P7: =IF(O7>Ipoteze!$B$11,"Neincasat","Incasat") -> Incasat
A8: 2026-07 | B8: 46206 | C8: NB-0770 | D8: SSD extern 1TB | E8: Stocare | F8: 17 | G8: 449 | H8: 290 | I8: Alfa Office SRL | J8: =F8*G8 -> 7633 | K8: =ROUND(J8*Ipoteze!$B$4,2) -> 1602.93 | L8: =J8+K8 -> 9235.93 | M8: =F8*H8 -> 4930 | N8: =INDEX(Clienti!$E:$E,MATCH(I8,Clienti!$A:$A,0)) -> 30 | O8: =B8+N8 -> 46236 | P8: =IF(O8>Ipoteze!$B$11,"Neincasat","Incasat") -> Incasat
A9: 2026-07 | B9: 46206 | C9: NB-0771 | D9: Incarcator GaN 65W | E9: Accesorii | F9: 1 | G9: 149 | H9: 75 | I9: Persoana fizica | J9: =F9*G9 -> 149 | K9: =ROUND(J9*Ipoteze!$B$4,2) -> 31.29 | L9: =J9+K9 -> 180.29 | M9: =F9*H9 -> 75 | N9: =INDEX(Clienti!$E:$E,MATCH(I9,Clienti!$A:$A,0)) -> 0 | O9: =B9+N9 -> 46206 | P9: =IF(O9>Ipoteze!$B$11,"Neincasat","Incasat") -> Incasat
A10: 2026-07 | B10: 46206 | C10: NB-0772 | D10: Hub USB-C 7in1 | E10: Accesorii | F10: 3 | G10: 169 | H10: 85 | I10: Online - eMag | J10: =F10*G10 -> 507 | K10: =ROUND(J10*Ipoteze!$B$4,2) -> 106.47 | L10: =J10+K10 -> 613.47 | M10: =F10*H10 -> 255 | N10: =INDEX(Clienti!$E:$E,MATCH(I10,Clienti!$A:$A,0)) -> 14 | O10: =B10+N10 -> 46220 | P10: =IF(O10>Ipoteze!$B$11,"Neincasat","Incasat") -> Incasat
A11: 2026-07 | B11: 46206 | C11: NB-0773 | D11: Casti over-ear H5 | E11: Audio | F11: 2 | G11: 219.5 | H11: 120 | I11: Persoana fizica | J11: =F11*G11 -> 439 | K11: =ROUND(J11*Ipoteze!$B$4,2) -> 92.19 | L11: =J11+K11 -> 531.19 | M11: =F11*H11 -> 240 | N11: =INDEX(Clienti!$E:$E,MATCH(I11,Clienti!$A:$A,0)) -> 0 | O11: =B11+N11 -> 46206 | P11: =IF(O11>Ipoteze!$B$11,"Neincasat","Incasat") -> Incasat
A12: 2026-07 | B12: 46207 | C12: NB-0774 | D12: Cablu USB-C 2m | E12: Cabluri | F12: 2 | G12: 29.99 | H12: 9 | I12: Online - eMag | J12: =F12*G12 -> 59.98 | K12: =ROUND(J12*Ipoteze!$B$4,2) -> 12.6 | L12: =J12+K12 -> 72.58 | M12: =F12*H12 -> 18 | N12: =INDEX(Clienti!$E:$E,MATCH(I12,Clienti!$A:$A,0)) -> 14 | O12: =B12+N12 -> 46221 | P12: =IF(O12>Ipoteze!$B$11,"Neincasat","Incasat") -> Incasat
A13: 2026-07 | B13: 46207 | C13: NB-0775 | D13: Tastatura mecanica K7 | E13: Periferice | F13: 2 | G13: 289 | H13: 160 | I13: Online - eMag | J13: =F13*G13 -> 578 | K13: =ROUND(J13*Ipoteze!$B$4,2) -> 121.38 | L13: =J13+K13 -> 699.38 | M13: =F13*H13 -> 320 | N13: =INDEX(Clienti!$E:$E,MATCH(I13,Clienti!$A:$A,0)) -> 14 | O13: =B13+N13 -> 46221 | P13: =IF(O13>Ipoteze!$B$11,"Neincasat","Incasat") -> Incasat
... A352: 2026-09 | B352: 46295 | C352: NB-1114 | D352: Cablu HDMI 2.1 3m | E352: Cabluri | F352: 1 | G352: 54.9 | H352: 22 | I352: Online - eMag | J352: =F352*G352 -> 54.9 | K352: =ROUND(J352*Ipoteze!$B$4,2) -> 11.53 | L352: =J352+K352 -> 66.43 | M352: =F352*H352 -> 22 | N352: =INDEX(Clienti!$E:$E,MATCH(I352,Clienti!$A:$A,0)) -> 14 | O352: =B352+N352 -> 46309 | P352: =IF(O352>Ipoteze!$B$11,"Neincasat","Incasat") -> Neincasat

Sheet Achizitii
A1: Luna | B1: Data | C1: Nr NIR | D1: Furnizor | E1: Cod produs | F1: Produs | G1: Cantitate | H1: Cost unitar fara TVA | I1: Valoare fara TVA | J1: TVA deductibil | K1: Total cu TVA
A2: 2026-07 | B2: 46205 | C2: NIR-439 | D2: Conex Distributie SRL | E2: P103 | F2: Mousepad XL | G2: 30 | H2: 19 | I2: =G2*H2 -> 570 | J2: =ROUND(I2*Ipoteze!$B$4,2) -> 119.7 | K2: =I2+J2 -> 689.7
A3: 2026-07 | B3: 46206 | C3: NIR-440 | D3: DataStore Distributie SRL | E3: P113 | F3: SSD extern 1TB | G3: 20 | H3: 290 | I3: =G3*H3 -> 5800 | J3: =ROUND(I3*Ipoteze!$B$4,2) -> 1218 | K3: =I3+J3 -> 7018
A4: 2026-07 | B4: 46206 | C4: NIR-441 | D4: TechSource Import SRL | E4: P109 | F4: Monitor 27 inch QHD | G4: 10 | H4: 780 | I4: =G4*H4 -> 7800 | J4: =ROUND(I4*Ipoteze!$B$4,2) -> 1638 | K4: =I4+J4 -> 9438
A5: 2026-07 | B5: 46209 | C5: NIR-442 | D5: Conex Distributie SRL | E5: P101 | F5: Hub USB-C 7in1 | G5: 30 | H5: 85 | I5: =G5*H5 -> 2550 | J5: =ROUND(I5*Ipoteze!$B$4,2) -> 535.5 | K5: =I5+J5 -> 3085.5
A6: 2026-07 | B6: 46210 | C6: NIR-443 | D6: DataStore Distributie SRL | E6: P114 | F6: Stick USB 64GB | G6: 10 | H6: 18 | I6: =G6*H6 -> 180 | J6: =ROUND(I6*Ipoteze!$B$4,2) -> 37.8 | K6: =I6+J6 -> 217.8
A7: 2026-07 | B7: 46211 | C7: NIR-444 | D7: TechSource Import SRL | E7: P112 | F7: Webcam FullHD C920 | G7: 30 | H7: 190 | I7: =G7*H7 -> 5700 | J7: =ROUND(I7*Ipoteze!$B$4,2) -> 1197 | K7: =I7+J7 -> 6897
A8: 2026-07 | B8: 46213 | C8: NIR-445 | D8: Conex Distributie SRL | E8: P107 | F8: Cablu HDMI 2.1 3m | G8: 20 | H8: 22 | I8: =G8*H8 -> 440 | J8: =ROUND(I8*Ipoteze!$B$4,2) -> 92.4 | K8: =I8+J8 -> 532.4
A9: 2026-07 | B9: 46213 | C9: NIR-445 | D9: Conex Distributie SRL | E9: P108 | F9: Cablu USB-C 2m | G9: 30 | H9: 9 | I9: =G9*H9 -> 270 | J9: =ROUND(I9*Ipoteze!$B$4,2) -> 56.7 | K9: =I9+J9 -> 326.7
A10: 2026-07 | B10: 46218 | C10: NIR-446 | D10: Conex Distributie SRL | E10: P103 | F10: Mousepad XL | G10: 30 | H10: 19 | I10: =G10*H10 -> 570 | J10: =ROUND(I10*Ipoteze!$B$4,2) -> 119.7 | K10: =I10+J10 -> 689.7
A11: 2026-07 | B11: 46219 | C11: NIR-447 | D11: Conex Distributie SRL | E11: P108 | F11: Cablu USB-C 2m | G11: 30 | H11: 9 | I11: =G11*H11 -> 270 | J11: =ROUND(I11*Ipoteze!$B$4,2) -> 56.7 | K11: =I11+J11 -> 326.7
A12: 2026-07 | B12: 46219 | C12: NIR-447 | D12: Conex Distributie SRL | E12: P102 | F12: Incarcator GaN 65W | G12: 30 | H12: 75 | I12: =G12*H12 -> 2250 | J12: =ROUND(I12*Ipoteze!$B$4,2) -> 472.5 | K12: =I12+J12 -> 2722.5
A13: 2026-07 | B13: 46219 | C13: NIR-448 | D13: SoundLine Trading SRL | E13: P105 | F13: Boxa bluetooth Mini | G13: 10 | H13: 70 | I13: =G13*H13 -> 700 | J13: =ROUND(I13*Ipoteze!$B$4,2) -> 147 | K13: =I13+J13 -> 847
... A107: 2026-09 | B107: 46295 | C107: NIR-526 | D107: DataStore Distributie SRL | E107: P113 | F107: SSD extern 1TB | G107: 20 | H107: 290 | I107: =G107*H107 -> 5800 | J107: =ROUND(I107*Ipoteze!$B$4,2) -> 1218 | K107: =I107+J107 -> 7018

Sheet Cheltuieli
A1: Luna | B1: Data | C1: Categorie | D1: Descriere | E1: Furnizor | F1: Suma fara TVA | G1: Cota TVA | H1: TVA deductibil | I1: Total cu TVA
A2: 2026-07 | B2: 46204 | C2: Chirie | D2: Chirie spatiu birou + depozit | E2: Imobiliare Centru SRL | F2: 6500 | G2: =Ipoteze!$B$4 -> 0.21 | H2: =ROUND(F2*G2,2) -> 1365 | I2: =F2+H2 -> 7865
A3: 2026-07 | B3: 46208 | C3: Utilitati | D3: Energie electrica iunie | E3: Enel Energie (fictiv) | F3: 1495.3 | G3: =Ipoteze!$B$4 -> 0.21 | H3: =ROUND(F3*G3,2) -> 314.01 | I3: =F3+H3 -> 1809.31
A4: 2026-07 | B4: 46208 | C4: Utilitati | D4: Apa si canalizare iunie | E4: Apa Nova (fictiv) | F4: 198.6 | G4: =Ipoteze!$B$5 -> 0.11 | H4: =ROUND(F4*G4,2) -> 21.85 | I4: =F4+H4 -> 220.45
A5: 2026-07 | B5: 46210 | C5: Utilitati | D5: Gaz iunie | E5: Engie (fictiv) | F5: 92.4 | G5: =Ipoteze!$B$4 -> 0.21 | H5: =ROUND(F5*G5,2) -> 19.4 | I5: =F5+H5 -> 111.8
A6: 2026-07 | B6: 46211 | C6: Utilitati | D6: Internet fibra + telefonie | E6: Digi (fictiv) | F6: 149 | G6: =Ipoteze!$B$4 -> 0.21 | H6: =ROUND(F6*G6,2) -> 31.29 | I6: =F6+H6 -> 180.29
A7: 2026-07 | B7: 46213 | C7: Contabilitate | D7: Servicii contabilitate iulie | E7: Cifra Exacta SRL | F7: 900 | G7: =Ipoteze!$B$4 -> 0.21 | H7: =ROUND(F7*G7,2) -> 189 | I7: =F7+H7 -> 1089
A8: 2026-07 | B8: 46215 | C8: Software | D8: Abonamente SaaS (facturare, email, cloud) | E8: Diversi | F8: 420 | G8: =Ipoteze!$B$4 -> 0.21 | H8: =ROUND(F8*G8,2) -> 88.2 | I8: =F8+H8 -> 508.2
A9: 2026-07 | B9: 46218 | C9: Marketing | D9: Reclame online iulie | E9: Meta / Google (fictiv) | F9: 2100 | G9: =Ipoteze!$B$4 -> 0.21 | H9: =ROUND(F9*G9,2) -> 441 | I9: =F9+H9 -> 2541
A10: 2026-07 | B10: 46221 | C10: Transport | D10: Curierat livrari | E10: FAN Courier (fictiv) | F10: 1045.2 | G10: =Ipoteze!$B$4 -> 0.21 | H10: =ROUND(F10*G10,2) -> 219.49 | I10: =F10+H10 -> 1264.69
A11: 2026-07 | B11: 46223 | C11: Consumabile | D11: Ambalaje, banda, etichete | E11: Pack Pro SRL | F11: 340.5 | G11: =Ipoteze!$B$4 -> 0.21 | H11: =ROUND(F11*G11,2) -> 71.51 | I11: =F11+H11 -> 412.01
A12: 2026-07 | B12: 46226 | C12: Mentenanta | D12: Reparatie raft metalic depozit | E12: Metal Rack Service SRL | F12: 620 | G12: =Ipoteze!$B$4 -> 0.21 | H12: =ROUND(F12*G12,2) -> 130.2 | I12: =F12+H12 -> 750.2
A13: 2026-07 | B13: 46231 | C13: Banca | D13: Comisioane bancare | E13: Banca fictiva | F13: 58.9 | G13: =0 -> 0 | H13: =ROUND(F13*G13,2) -> 0 | I13: =F13+H13 -> 58.9
A14: 2026-08 | B14: 46235 | C14: Chirie | D14: Chirie spatiu birou + depozit | E14: Imobiliare Centru SRL | F14: 6500 | G14: =Ipoteze!$B$4 -> 0.21 | H14: =ROUND(F14*G14,2) -> 1365 | I14: =F14+H14 -> 7865
A15: 2026-08 | B15: 46239 | C15: Utilitati | D15: Energie electrica iulie | E15: Enel Energie (fictiv) | F15: 1612.85 | G15: =Ipoteze!$B$4 -> 0.21 | H15: =ROUND(F15*G15,2) -> 338.7 | I15: =F15+H15 -> 1951.55
A16: 2026-08 | B16: 46239 | C16: Utilitati | D16: Apa si canalizare iulie | E16: Apa Nova (fictiv) | F16: 221.1 | G16: =Ipoteze!$B$5 -> 0.11 | H16: =ROUND(F16*G16,2) -> 24.32 | I16: =F16+H16 -> 245.42
A17: 2026-08 | B17: 46241 | C17: Utilitati | D17: Gaz iulie | E17: Engie (fictiv) | F17: 78.6 | G17: =Ipoteze!$B$4 -> 0.21 | H17: =ROUND(F17*G17,2) -> 16.51 | I17: =F17+H17 -> 95.11
A18: 2026-08 | B18: 46242 | C18: Utilitati | D18: Internet fibra + telefonie | E18: Digi (fictiv) | F18: 149 | G18: =Ipoteze!$B$4 -> 0.21 | H18: =ROUND(F18*G18,2) -> 31.29 | I18: =F18+H18 -> 180.29
A19: 2026-08 | B19: 46244 | C19: Contabilitate | D19: Servicii contabilitate august | E19: Cifra Exacta SRL | F19: 900 | G19: =Ipoteze!$B$4 -> 0.21 | H19: =ROUND(F19*G19,2) -> 189 | I19: =F19+H19 -> 1089
A20: 2026-08 | B20: 46246 | C20: Software | D20: Abonamente SaaS (facturare, email, cloud) | E20: Diversi | F20: 420 | G20: =Ipoteze!$B$4 -> 0.21 | H20: =ROUND(F20*G20,2) -> 88.2 | I20: =F20+H20 -> 508.2
A21: 2026-08 | B21: 46248 | C21: Marketing | D21: Reclame online august (campanie back-to-school) | E21: Meta / Google (fictiv) | F21: 2650 | G21: =Ipoteze!$B$4 -> 0.21 | H21: =ROUND(F21*G21,2) -> 556.5 | I21: =F21+H21 -> 3206.5
A22: 2026-08 | B22: 46252 | C22: Transport | D22: Curierat livrari | E22: FAN Courier (fictiv) | F22: 985.7 | G22: =Ipoteze!$B$4 -> 0.21 | H22: =ROUND(F22*G22,2) -> 207 | I22: =F22+H22 -> 1192.7
A23: 2026-08 | B23: 46254 | C23: Consumabile | D23: Ambalaje, banda, etichete | E23: Pack Pro SRL | F23: 310.25 | G23: =Ipoteze!$B$4 -> 0.21 | H23: =ROUND(F23*G23,2) -> 65.15 | I23: =F23+H23 -> 375.4
A24: 2026-08 | B24: 46258 | C24: Echipamente IT | D24: Imprimanta etichete termice | E24: Office Direct SRL | F24: 780 | G24: =Ipoteze!$B$4 -> 0.21 | H24: =ROUND(F24*G24,2) -> 163.8 | I24: =F24+H24 -> 943.8
A25: 2026-08 | B25: 46262 | C25: Banca | D25: Comisioane bancare | E25: Banca fictiva | F25: 55.4 | G25: =0 -> 0 | H25: =ROUND(F25*G25,2) -> 0 | I25: =F25+H25 -> 55.4
A26: 2026-09 | B26: 46266 | C26: Chirie | D26: Chirie spatiu birou + depozit | E26: Imobiliare Centru SRL | F26: 6500 | G26: =Ipoteze!$B$4 -> 0.21 | H26: =ROUND(F26*G26,2) -> 1365 | I26: =F26+H26 -> 7865
A27: 2026-09 | B27: 46270 | C27: Utilitati | D27: Energie electrica august | E27: Enel Energie (fictiv) | F27: 1340.75 | G27: =Ipoteze!$B$4 -> 0.21 | H27: =ROUND(F27*G27,2) -> 281.56 | I27: =F27+H27 -> 1622.31
A28: 2026-09 | B28: 46270 | C28: Utilitati | D28: Apa si canalizare august | E28: Apa Nova (fictiv) | F28: 210.4 | G28: =Ipoteze!$B$5 -> 0.11 | H28: =ROUND(F28*G28,2) -> 23.14 | I28: =F28+H28 -> 233.54
A29: 2026-09 | B29: 46272 | C29: Utilitati | D29: Gaz august | E29: Engie (fictiv) | F29: 185.2 | G29: =Ipoteze!$B$4 -> 0.21 | H29: =ROUND(F29*G29,2) -> 38.89 | I29: =F29+H29 -> 224.09
A30: 2026-09 | B30: 46273 | C30: Utilitati | D30: Internet fibra + telefonie | E30: Digi (fictiv) | F30: 149 | G30: =Ipoteze!$B$4 -> 0.21 | H30: =ROUND(F30*G30,2) -> 31.29 | I30: =F30+H30 -> 180.29
A31: 2026-09 | B31: 46275 | C31: Contabilitate | D31: Servicii contabilitate septembrie | E31: Cifra Exacta SRL | F31: 900 | G31: =Ipoteze!$B$4 -> 0.21 | H31: =ROUND(F31*G31,2) -> 189 | I31: =F31+H31 -> 1089
A32: 2026-09 | B32: 46277 | C32: Software | D32: Abonamente SaaS (facturare, email, cloud) | E32: Diversi | F32: 420 | G32: =Ipoteze!$B$4 -> 0.21 | H32: =ROUND(F32*G32,2) -> 88.2 | I32: =F32+H32 -> 508.2
A33: 2026-09 | B33: 46280 | C33: Marketing | D33: Reclame online septembrie | E33: Meta / Google (fictiv) | F33: 2300 | G33: =Ipoteze!$B$4 -> 0.21 | H33: =ROUND(F33*G33,2) -> 483 | I33: =F33+H33 -> 2783
A34: 2026-09 | B34: 46283 | C34: Transport | D34: Curierat livrari | E34: FAN Courier (fictiv) | F34: 1120.5 | G34: =Ipoteze!$B$4 -> 0.21 | H34: =ROUND(F34*G34,2) -> 235.31 | I34: =F34+H34 -> 1355.81
A35: 2026-09 | B35: 46285 | C35: Consumabile | D35: Ambalaje, banda, etichete | E35: Pack Pro SRL | F35: 365.8 | G35: =Ipoteze!$B$4 -> 0.21 | H35: =ROUND(F35*G35,2) -> 76.82 | I35: =F35+H35 -> 442.62
A36: 2026-09 | B36: 46290 | C36: Mentenanta | D36: Revizie aer conditionat | E36: Clima Service SRL | F36: 450 | G36: =Ipoteze!$B$4 -> 0.21 | H36: =ROUND(F36*G36,2) -> 94.5 | I36: =F36+H36 -> 544.5
A37: 2026-09 | B37: 46293 | C37: Banca | D37: Comisioane bancare | E37: Banca fictiva | F37: 62.3 | G37: =0 -> 0 | H37: =ROUND(F37*G37,2) -> 0 | I37: =F37+H37 -> 62.3
A39: Nota: comisioanele bancare sunt scutite de TVA; apa/canalizare are cota redusa.

Sheet Salarii
A1: Luna | B1: Nume | C1: Functie | D1: Zile lucrate | E1: Salariu brut | F1: CAS 25% | G1: CASS 10% | H1: Baza impozabila | I1: Impozit 10% | J1: Salariu net | K1: CAM 2,25% | L1: Cost total angajator
A2: 2026-07 | B2: Andrei Popescu | C2: Director general | D2: 23 | E2: 9500 | F2: =ROUND(E2*Ipoteze!$B$6,0) -> 2375 | G2: =ROUND(E2*Ipoteze!$B$7,0) -> 950 | H2: =E2-F2-G2 -> 6175 | I2: =ROUND(H2*Ipoteze!$B$8,0) -> 618 | J2: =H2-I2 -> 5557 | K2: =ROUND(E2*Ipoteze!$B$9,0) -> 214 | L2: =E2+K2 -> 9714
A3: 2026-07 | B3: Ioana Marin | C3: Contabil intern | D3: 23 | E3: 6200 | F3: =ROUND(E3*Ipoteze!$B$6,0) -> 1550 | G3: =ROUND(E3*Ipoteze!$B$7,0) -> 620 | H3: =E3-F3-G3 -> 4030 | I3: =ROUND(H3*Ipoteze!$B$8,0) -> 403 | J3: =H3-I3 -> 3627 | K3: =ROUND(E3*Ipoteze!$B$9,0) -> 140 | L3: =E3+K3 -> 6340
A4: 2026-07 | B4: Mihai Dobre | C4: Agent vanzari | D4: 23 | E4: 5000 | F4: =ROUND(E4*Ipoteze!$B$6,0) -> 1250 | G4: =ROUND(E4*Ipoteze!$B$7,0) -> 500 | H4: =E4-F4-G4 -> 3250 | I4: =ROUND(H4*Ipoteze!$B$8,0) -> 325 | J4: =H4-I4 -> 2925 | K4: =ROUND(E4*Ipoteze!$B$9,0) -> 113 | L4: =E4+K4 -> 5113
A5: 2026-07 | B5: Elena Stan | C5: Agent vanzari | D5: 23 | E5: 5000 | F5: =ROUND(E5*Ipoteze!$B$6,0) -> 1250 | G5: =ROUND(E5*Ipoteze!$B$7,0) -> 500 | H5: =E5-F5-G5 -> 3250 | I5: =ROUND(H5*Ipoteze!$B$8,0) -> 325 | J5: =H5-I5 -> 2925 | K5: =ROUND(E5*Ipoteze!$B$9,0) -> 113 | L5: =E5+K5 -> 5113
A6: 2026-07 | B6: Radu Ilie | C6: Gestionar depozit | D6: 23 | E6: 4325 | F6: =ROUND(E6*Ipoteze!$B$6,0) -> 1081 | G6: =ROUND(E6*Ipoteze!$B$7,0) -> 433 | H6: =E6-F6-G6 -> 2811 | I6: =ROUND(H6*Ipoteze!$B$8,0) -> 281 | J6: =H6-I6 -> 2530 | K6: =ROUND(E6*Ipoteze!$B$9,0) -> 97 | L6: =E6+K6 -> 4422
A7: 2026-07 | B7: Cristina Vlad | C7: Customer support | D7: 23 | E7: 4500 | F7: =ROUND(E7*Ipoteze!$B$6,0) -> 1125 | G7: =ROUND(E7*Ipoteze!$B$7,0) -> 450 | H7: =E7-F7-G7 -> 2925 | I7: =ROUND(H7*Ipoteze!$B$8,0) -> 293 | J7: =H7-I7 -> 2632 | K7: =ROUND(E7*Ipoteze!$B$9,0) -> 101 | L7: =E7+K7 -> 4601
A8: 2026-08 | B8: Andrei Popescu | C8: Director general | D8: 21 | E8: 9500 | F8: =ROUND(E8*Ipoteze!$B$6,0) -> 2375 | G8: =ROUND(E8*Ipoteze!$B$7,0) -> 950 | H8: =E8-F8-G8 -> 6175 | I8: =ROUND(H8*Ipoteze!$B$8,0) -> 618 | J8: =H8-I8 -> 5557 | K8: =ROUND(E8*Ipoteze!$B$9,0) -> 214 | L8: =E8+K8 -> 9714
A9: 2026-08 | B9: Ioana Marin | C9: Contabil intern | D9: 21 | E9: 6200 | F9: =ROUND(E9*Ipoteze!$B$6,0) -> 1550 | G9: =ROUND(E9*Ipoteze!$B$7,0) -> 620 | H9: =E9-F9-G9 -> 4030 | I9: =ROUND(H9*Ipoteze!$B$8,0) -> 403 | J9: =H9-I9 -> 3627 | K9: =ROUND(E9*Ipoteze!$B$9,0) -> 140 | L9: =E9+K9 -> 6340
A10: 2026-08 | B10: Mihai Dobre | C10: Agent vanzari | D10: 21 | E10: 5000 | F10: =ROUND(E10*Ipoteze!$B$6,0) -> 1250 | G10: =ROUND(E10*Ipoteze!$B$7,0) -> 500 | H10: =E10-F10-G10 -> 3250 | I10: =ROUND(H10*Ipoteze!$B$8,0) -> 325 | J10: =H10-I10 -> 2925 | K10: =ROUND(E10*Ipoteze!$B$9,0) -> 113 | L10: =E10+K10 -> 5113
A11: 2026-08 | B11: Elena Stan | C11: Agent vanzari | D11: 21 | E11: 5000 | F11: =ROUND(E11*Ipoteze!$B$6,0) -> 1250 | G11: =ROUND(E11*Ipoteze!$B$7,0) -> 500 | H11: =E11-F11-G11 -> 3250 | I11: =ROUND(H11*Ipoteze!$B$8,0) -> 325 | J11: =H11-I11 -> 2925 | K11: =ROUND(E11*Ipoteze!$B$9,0) -> 113 | L11: =E11+K11 -> 5113
A12: 2026-08 | B12: Radu Ilie | C12: Gestionar depozit | D12: 21 | E12: 4325 | F12: =ROUND(E12*Ipoteze!$B$6,0) -> 1081 | G12: =ROUND(E12*Ipoteze!$B$7,0) -> 433 | H12: =E12-F12-G12 -> 2811 | I12: =ROUND(H12*Ipoteze!$B$8,0) -> 281 | J12: =H12-I12 -> 2530 | K12: =ROUND(E12*Ipoteze!$B$9,0) -> 97 | L12: =E12+K12 -> 4422
A13: 2026-08 | B13: Cristina Vlad | C13: Customer support | D13: 21 | E13: 4500 | F13: =ROUND(E13*Ipoteze!$B$6,0) -> 1125 | G13: =ROUND(E13*Ipoteze!$B$7,0) -> 450 | H13: =E13-F13-G13 -> 2925 | I13: =ROUND(H13*Ipoteze!$B$8,0) -> 293 | J13: =H13-I13 -> 2632 | K13: =ROUND(E13*Ipoteze!$B$9,0) -> 101 | L13: =E13+K13 -> 4601
... A19: 2026-09 | B19: Cristina Vlad | C19: Customer support | D19: 22 | E19: 4500 | F19: =ROUND(E19*Ipoteze!$B$6,0) -> 1125 | G19: =ROUND(E19*Ipoteze!$B$7,0) -> 450 | H19: =E19-F19-G19 -> 2925 | I19: =ROUND(H19*Ipoteze!$B$8,0) -> 293 | J19: =H19-I19 -> 2632 | K19: =ROUND(E19*Ipoteze!$B$9,0) -> 101 | L19: =E19+K19 -> 4601

Sheet Stocuri
A1: Luna | B1: Cod produs | C1: Produs | D1: Stoc initial | E1: Intrari (NIR) | F1: Iesiri (vanzari) | G1: Stoc final | H1: Cost unitar | I1: Valoare stoc final | J1: Control: initial = final luna anterioara
A2: 2026-07 | B2: P101 | C2: Hub USB-C 7in1 | D2: 34 | E2: =SUMIFS(Achizitii!$G:$G,Achizitii!$A:$A,A2,Achizitii!$E:$E,B2) -> 60 | F2: =SUMIFS(Vanzari!$F:$F,Vanzari!$A:$A,A2,Vanzari!$D:$D,C2) -> 78 | G2: =D2+E2-F2 -> 16 | H2: 85 | I2: =G2*H2 -> 1360 | J2: Stoc de deschidere
A3: 2026-07 | B3: P102 | C3: Incarcator GaN 65W | D3: 40 | E3: =SUMIFS(Achizitii!$G:$G,Achizitii!$A:$A,A3,Achizitii!$E:$E,B3) -> 90 | F3: =SUMIFS(Vanzari!$F:$F,Vanzari!$A:$A,A3,Vanzari!$D:$D,C3) -> 78 | G3: =D3+E3-F3 -> 52 | H3: 75 | I3: =G3*H3 -> 3900 | J3: Stoc de deschidere
A4: 2026-07 | B4: P103 | C4: Mousepad XL | D4: 19 | E4: =SUMIFS(Achizitii!$G:$G,Achizitii!$A:$A,A4,Achizitii!$E:$E,B4) -> 60 | F4: =SUMIFS(Vanzari!$F:$F,Vanzari!$A:$A,A4,Vanzari!$D:$D,C4) -> 72 | G4: =D4+E4-F4 -> 7 | H4: 19 | I4: =G4*H4 -> 133 | J4: Stoc de deschidere
A5: 2026-07 | B5: P104 | C5: Suport laptop aluminiu | D5: 13 | E5: =SUMIFS(Achizitii!$G:$G,Achizitii!$A:$A,A5,Achizitii!$E:$E,B5) -> 10 | F5: =SUMIFS(Vanzari!$F:$F,Vanzari!$A:$A,A5,Vanzari!$D:$D,C5) -> 9 | G5: =D5+E5-F5 -> 14 | H5: 48 | I5: =G5*H5 -> 672 | J5: Stoc de deschidere
A6: 2026-07 | B6: P105 | C6: Boxa bluetooth Mini | D6: 10 | E6: =SUMIFS(Achizitii!$G:$G,Achizitii!$A:$A,A6,Achizitii!$E:$E,B6) -> 50 | F6: =SUMIFS(Vanzari!$F:$F,Vanzari!$A:$A,A6,Vanzari!$D:$D,C6) -> 27 | G6: =D6+E6-F6 -> 33 | H6: 70 | I6: =G6*H6 -> 2310 | J6: Stoc de deschidere
A7: 2026-07 | B7: P106 | C7: Casti over-ear H5 | D7: 24 | E7: =SUMIFS(Achizitii!$G:$G,Achizitii!$A:$A,A7,Achizitii!$E:$E,B7) -> 90 | F7: =SUMIFS(Vanzari!$F:$F,Vanzari!$A:$A,A7,Vanzari!$D:$D,C7) -> 41 | G7: =D7+E7-F7 -> 73 | H7: 120 | I7: =G7*H7 -> 8760 | J7: Stoc de deschidere
A8: 2026-07 | B8: P107 | C8: Cablu HDMI 2.1 3m | D8: 40 | E8: =SUMIFS(Achizitii!$G:$G,Achizitii!$A:$A,A8,Achizitii!$E:$E,B8) -> 40 | F8: =SUMIFS(Vanzari!$F:$F,Vanzari!$A:$A,A8,Vanzari!$D:$D,C8) -> 50 | G8: =D8+E8-F8 -> 30 | H8: 22 | I8: =G8*H8 -> 660 | J8: Stoc de deschidere
A9: 2026-07 | B9: P108 | C9: Cablu USB-C 2m | D9: 33 | E9: =SUMIFS(Achizitii!$G:$G,Achizitii!$A:$A,A9,Achizitii!$E:$E,B9) -> 90 | F9: =SUMIFS(Vanzari!$F:$F,Vanzari!$A:$A,A9,Vanzari!$D:$D,C9) -> 77 | G9: =D9+E9-F9 -> 46 | H9: 9 | I9: =G9*H9 -> 414 | J9: Stoc de deschidere
A10: 2026-07 | B10: P109 | C10: Monitor 27 inch QHD | D10: 7 | E10: =SUMIFS(Achizitii!$G:$G,Achizitii!$A:$A,A10,Achizitii!$E:$E,B10) -> 30 | F10: =SUMIFS(Vanzari!$F:$F,Vanzari!$A:$A,A10,Vanzari!$D:$D,C10) -> 25 | G10: =D10+E10-F10 -> 12 | H10: 780 | I10: =G10*H10 -> 9360 | J10: Stoc de deschidere
A11: 2026-07 | B11: P110 | C11: Mouse wireless M200 | D11: 18 | E11: =SUMIFS(Achizitii!$G:$G,Achizitii!$A:$A,A11,Achizitii!$E:$E,B11) -> 60 | F11: =SUMIFS(Vanzari!$F:$F,Vanzari!$A:$A,A11,Vanzari!$D:$D,C11) -> 36 | G11: =D11+E11-F11 -> 42 | H11: 45 | I11: =G11*H11 -> 1890 | J11: Stoc de deschidere
A12: 2026-07 | B12: P111 | C12: Tastatura mecanica K7 | D12: 38 | E12: =SUMIFS(Achizitii!$G:$G,Achizitii!$A:$A,A12,Achizitii!$E:$E,B12) -> 50 | F12: =SUMIFS(Vanzari!$F:$F,Vanzari!$A:$A,A12,Vanzari!$D:$D,C12) -> 68 | G12: =D12+E12-F12 -> 20 | H12: 160 | I12: =G12*H12 -> 3200 | J12: Stoc de deschidere
A13: 2026-07 | B13: P112 | C13: Webcam FullHD C920 | D13: 30 | E13: =SUMIFS(Achizitii!$G:$G,Achizitii!$A:$A,A13,Achizitii!$E:$E,B13) -> 60 | F13: =SUMIFS(Vanzari!$F:$F,Vanzari!$A:$A,A13,Vanzari!$D:$D,C13) -> 81 | G13: =D13+E13-F13 -> 9 | H13: 190 | I13: =G13*H13 -> 1710 | J13: Stoc de deschidere
... A15: 2026-07 | B15: P114 | C15: Stick USB 64GB | D15: 10 | E15: =SUMIFS(Achizitii!$G:$G,Achizitii!$A:$A,A15,Achizitii!$E:$E,B15) -> 30 | F15: =SUMIFS(Vanzari!$F:$F,Vanzari!$A:$A,A15,Vanzari!$D:$D,C15) -> 29 | G15: =D15+E15-F15 -> 11 | H15: 18 | I15: =G15*H15 -> 198 | J15: Stoc de deschidere
A16: 2026-08 | B16: P101 | C16: Hub USB-C 7in1 | D16: =G2 -> 16 | E16: =SUMIFS(Achizitii!$G:$G,Achizitii!$A:$A,A16,Achizitii!$E:$E,B16) -> 10 | F16: =SUMIFS(Vanzari!$F:$F,Vanzari!$A:$A,A16,Vanzari!$D:$D,C16) -> 16 | G16: =D16+E16-F16 -> 10 | H16: 85 | I16: =G16*H16 -> 850 | J16: =IF(D16=G2,"OK","Diferenta") -> OK
A17: 2026-08 | B17: P102 | C17: Incarcator GaN 65W | D17: =G3 -> 52 | E17: =SUMIFS(Achizitii!$G:$G,Achizitii!$A:$A,A17,Achizitii!$E:$E,B17) -> 70 | F17: =SUMIFS(Vanzari!$F:$F,Vanzari!$A:$A,A17,Vanzari!$D:$D,C17) -> 87 | G17: =D17+E17-F17 -> 35 | H17: 75 | I17: =G17*H17 -> 2625 | J17: =IF(D17=G3,"OK","Diferenta") -> OK
A18: 2026-08 | B18: P103 | C18: Mousepad XL | D18: =G4 -> 7 | E18: =SUMIFS(Achizitii!$G:$G,Achizitii!$A:$A,A18,Achizitii!$E:$E,B18) -> 60 | F18: =SUMIFS(Vanzari!$F:$F,Vanzari!$A:$A,A18,Vanzari!$D:$D,C18) -> 20 | G18: =D18+E18-F18 -> 47 | H18: 19 | I18: =G18*H18 -> 893 | J18: =IF(D18=G4,"OK","Diferenta") -> OK
A19: 2026-08 | B19: P104 | C19: Suport laptop aluminiu | D19: =G5 -> 14 | E19: =SUMIFS(Achizitii!$G:$G,Achizitii!$A:$A,A19,Achizitii!$E:$E,B19) -> 20 | F19: =SUMIFS(Vanzari!$F:$F,Vanzari!$A:$A,A19,Vanzari!$D:$D,C19) -> 26 | G19: =D19+E19-F19 -> 8 | H19: 48 | I19: =G19*H19 -> 384 | J19: =IF(D19=G5,"OK","Diferenta") -> OK
A20: 2026-08 | B20: P105 | C20: Boxa bluetooth Mini | D20: =G6 -> 33 | E20: =SUMIFS(Achizitii!$G:$G,Achizitii!$A:$A,A20,Achizitii!$E:$E,B20) -> 120 | F20: =SUMIFS(Vanzari!$F:$F,Vanzari!$A:$A,A20,Vanzari!$D:$D,C20) -> 100 | G20: =D20+E20-F20 -> 53 | H20: 70 | I20: =G20*H20 -> 3710 | J20: =IF(D20=G6,"OK","Diferenta") -> OK
A21: 2026-08 | B21: P106 | C21: Casti over-ear H5 | D21: =G7 -> 73 | E21: =SUMIFS(Achizitii!$G:$G,Achizitii!$A:$A,A21,Achizitii!$E:$E,B21) -> 35 | F21: =SUMIFS(Vanzari!$F:$F,Vanzari!$A:$A,A21,Vanzari!$D:$D,C21) -> 90 | G21: =D21+E21-F21 -> 18 | H21: 120 | I21: =G21*H21 -> 2160 | J21: =IF(D21=G7,"OK","Diferenta") -> OK
A22: 2026-08 | B22: P107 | C22: Cablu HDMI 2.1 3m | D22: =G8 -> 30 | E22: =SUMIFS(Achizitii!$G:$G,Achizitii!$A:$A,A22,Achizitii!$E:$E,B22) -> 40 | F22: =SUMIFS(Vanzari!$F:$F,Vanzari!$A:$A,A22,Vanzari!$D:$D,C22) -> 45 | G22: =D22+E22-F22 -> 25 | H22: 22 | I22: =G22*H22 -> 550 | J22: =IF(D22=G8,"OK","Diferenta") -> OK
A23: 2026-08 | B23: P108 | C23: Cablu USB-C 2m | D23: =G9 -> 46 | E23: =SUMIFS(Achizitii!$G:$G,Achizitii!$A:$A,A23,Achizitii!$E:$E,B23) -> 60 | F23: =SUMIFS(Vanzari!$F:$F,Vanzari!$A:$A,A23,Vanzari!$D:$D,C23) -> 72 | G23: =D23+E23-F23 -> 34 | H23: 9 | I23: =G23*H23 -> 306 | J23: =IF(D23=G9,"OK","Diferenta") -> OK
A24: 2026-08 | B24: P109 | C24: Monitor 27 inch QHD | D24: =G10 -> 12 | E24: =SUMIFS(Achizitii!$G:$G,Achizitii!$A:$A,A24,Achizitii!$E:$E,B24) -> 0 | F24: =SUMIFS(Vanzari!$F:$F,Vanzari!$A:$A,A24,Vanzari!$D:$D,C24) -> 8 | G24: =D24+E24-F24 -> 4 | H24: 780 | I24: =G24*H24 -> 3120 | J24: =IF(D24=G10,"OK","Diferenta") -> OK
A25: 2026-08 | B25: P110 | C25: Mouse wireless M200 | D25: =G11 -> 42 | E25: =SUMIFS(Achizitii!$G:$G,Achizitii!$A:$A,A25,Achizitii!$E:$E,B25) -> 60 | F25: =SUMIFS(Vanzari!$F:$F,Vanzari!$A:$A,A25,Vanzari!$D:$D,C25) -> 79 | G25: =D25+E25-F25 -> 23 | H25: 45 | I25: =G25*H25 -> 1035 | J25: =IF(D25=G11,"OK","Diferenta") -> OK
A26: 2026-08 | B26: P111 | C26: Tastatura mecanica K7 | D26: =G12 -> 20 | E26: =SUMIFS(Achizitii!$G:$G,Achizitii!$A:$A,A26,Achizitii!$E:$E,B26) -> 90 | F26: =SUMIFS(Vanzari!$F:$F,Vanzari!$A:$A,A26,Vanzari!$D:$D,C26) -> 73 | G26: =D26+E26-F26 -> 37 | H26: 160 | I26: =G26*H26 -> 5920 | J26: =IF(D26=G12,"OK","Diferenta") -> OK
A27: 2026-08 | B27: P112 | C27: Webcam FullHD C920 | D27: =G13 -> 9 | E27: =SUMIFS(Achizitii!$G:$G,Achizitii!$A:$A,A27,Achizitii!$E:$E,B27) -> 40 | F27: =SUMIFS(Vanzari!$F:$F,Vanzari!$A:$A,A27,Vanzari!$D:$D,C27) -> 22 | G27: =D27+E27-F27 -> 27 | H27: 190 | I27: =G27*H27 -> 5130 | J27: =IF(D27=G13,"OK","Diferenta") -> OK
... A43: 2026-09 | B43: P114 | C43: Stick USB 64GB | D43: =G29 -> 23 | E43: =SUMIFS(Achizitii!$G:$G,Achizitii!$A:$A,A43,Achizitii!$E:$E,B43) -> 40 | F43: =SUMIFS(Vanzari!$F:$F,Vanzari!$A:$A,A43,Vanzari!$D:$D,C43) -> 45 | G43: =D43+E43-F43 -> 18 | H43: 18 | I43: =G43*H43 -> 324 | J43: =IF(D43=G29,"OK","Diferenta") -> OK

Sheet Clienti
A1: Client | B1: Tip client | C1: Oras | D1: Agent responsabil | E1: Termen plata (zile) | F1: Vanzari iulie | G1: Vanzari august | H1: Vanzari septembrie | I1: Total trimestru | J1: Creante la 30.09 (cu TVA)
A2: Alfa Office SRL | B2: B2B | C2: Bucuresti | D2: Mihai Dobre | E2: 30 | F2: =SUMIFS(Vanzari!$J:$J,Vanzari!$I:$I,$A2,Vanzari!$A:$A,"2026-07") -> 42280.04 | G2: =SUMIFS(Vanzari!$J:$J,Vanzari!$I:$I,$A2,Vanzari!$A:$A,"2026-08") -> 20458.28 | H2: =SUMIFS(Vanzari!$J:$J,Vanzari!$I:$I,$A2,Vanzari!$A:$A,"2026-09") -> 31105.05 | I2: =SUM(F2:H2) -> 93843.37 | J2: =SUMIFS(Vanzari!$L:$L,Vanzari!$I:$I,$A2,Vanzari!$P:$P,"Neincasat") -> 37637.12
A3: Beta Studio SRL | B3: B2B | C3: Cluj-Napoca | D3: Elena Stan | E3: 15 | F3: =SUMIFS(Vanzari!$J:$J,Vanzari!$I:$I,$A3,Vanzari!$A:$A,"2026-07") -> 15265.62 | G3: =SUMIFS(Vanzari!$J:$J,Vanzari!$I:$I,$A3,Vanzari!$A:$A,"2026-08") -> 11179.95 | H3: =SUMIFS(Vanzari!$J:$J,Vanzari!$I:$I,$A3,Vanzari!$A:$A,"2026-09") -> 21702.68 | I3: =SUM(F3:H3) -> 48148.25 | J3: =SUMIFS(Vanzari!$L:$L,Vanzari!$I:$I,$A3,Vanzari!$P:$P,"Neincasat") -> 22695.24
A4: Delta Design SRL | B4: B2B | C4: Brasov | D4: Elena Stan | E4: 15 | F4: =SUMIFS(Vanzari!$J:$J,Vanzari!$I:$I,$A4,Vanzari!$A:$A,"2026-07") -> 13364.76 | G4: =SUMIFS(Vanzari!$J:$J,Vanzari!$I:$I,$A4,Vanzari!$A:$A,"2026-08") -> 35025.68 | H4: =SUMIFS(Vanzari!$J:$J,Vanzari!$I:$I,$A4,Vanzari!$A:$A,"2026-09") -> 23109.01 | I4: =SUM(F4:H4) -> 71499.45 | J4: =SUMIFS(Vanzari!$L:$L,Vanzari!$I:$I,$A4,Vanzari!$P:$P,"Neincasat") -> 7261.71
A5: Gamma Logistic SRL | B5: B2B | C5: Ploiesti | D5: Mihai Dobre | E5: 30 | F5: =SUMIFS(Vanzari!$J:$J,Vanzari!$I:$I,$A5,Vanzari!$A:$A,"2026-07") -> 29249.4 | G5: =SUMIFS(Vanzari!$J:$J,Vanzari!$I:$I,$A5,Vanzari!$A:$A,"2026-08") -> 21048.6 | H5: =SUMIFS(Vanzari!$J:$J,Vanzari!$I:$I,$A5,Vanzari!$A:$A,"2026-09") -> 29976.7 | I5: =SUM(F5:H5) -> 80274.7 | J5: =SUMIFS(Vanzari!$L:$L,Vanzari!$I:$I,$A5,Vanzari!$P:$P,"Neincasat") -> 36271.8
A6: Omega Consult SRL | B6: B2B | C6: Timisoara | D6: Elena Stan | E6: 30 | F6: =SUMIFS(Vanzari!$J:$J,Vanzari!$I:$I,$A6,Vanzari!$A:$A,"2026-07") -> 30350.69 | G6: =SUMIFS(Vanzari!$J:$J,Vanzari!$I:$I,$A6,Vanzari!$A:$A,"2026-08") -> 14058.79 | H6: =SUMIFS(Vanzari!$J:$J,Vanzari!$I:$I,$A6,Vanzari!$A:$A,"2026-09") -> 27207.43 | I6: =SUM(F6:H6) -> 71616.91 | J6: =SUMIFS(Vanzari!$L:$L,Vanzari!$I:$I,$A6,Vanzari!$P:$P,"Neincasat") -> 32920.99
A7: Online - eMag | B7: Marketplace | C7: - | D7: - | E7: 14 | F7: =SUMIFS(Vanzari!$J:$J,Vanzari!$I:$I,$A7,Vanzari!$A:$A,"2026-07") -> 7532.68 | G7: =SUMIFS(Vanzari!$J:$J,Vanzari!$I:$I,$A7,Vanzari!$A:$A,"2026-08") -> 5279.79 | H7: =SUMIFS(Vanzari!$J:$J,Vanzari!$I:$I,$A7,Vanzari!$A:$A,"2026-09") -> 7337.15 | I7: =SUM(F7:H7) -> 20149.62 | J7: =SUMIFS(Vanzari!$L:$L,Vanzari!$I:$I,$A7,Vanzari!$P:$P,"Neincasat") -> 4859.85
A8: Online - site propriu | B8: Online | C8: - | D8: - | E8: 0 | F8: =SUMIFS(Vanzari!$J:$J,Vanzari!$I:$I,$A8,Vanzari!$A:$A,"2026-07") -> 3660.85 | G8: =SUMIFS(Vanzari!$J:$J,Vanzari!$I:$I,$A8,Vanzari!$A:$A,"2026-08") -> 7408.4 | H8: =SUMIFS(Vanzari!$J:$J,Vanzari!$I:$I,$A8,Vanzari!$A:$A,"2026-09") -> 5341.72 | I8: =SUM(F8:H8) -> 16410.97 | J8: =SUMIFS(Vanzari!$L:$L,Vanzari!$I:$I,$A8,Vanzari!$P:$P,"Neincasat") -> 0
A9: Persoana fizica | B9: B2C | C9: - | D9: - | E9: 0 | F9: =SUMIFS(Vanzari!$J:$J,Vanzari!$I:$I,$A9,Vanzari!$A:$A,"2026-07") -> 7731.53 | G9: =SUMIFS(Vanzari!$J:$J,Vanzari!$I:$I,$A9,Vanzari!$A:$A,"2026-08") -> 9958.7 | H9: =SUMIFS(Vanzari!$J:$J,Vanzari!$I:$I,$A9,Vanzari!$A:$A,"2026-09") -> 6874.88 | I9: =SUM(F9:H9) -> 24565.11 | J9: =SUMIFS(Vanzari!$L:$L,Vanzari!$I:$I,$A9,Vanzari!$P:$P,"Neincasat") -> 0
A10: TOTAL | F10: =SUM(F2:F9) -> 149435.57 | G10: =SUM(G2:G9) -> 124418.19 | H10: =SUM(H2:H9) -> 152654.62 | I10: =SUM(I2:I9) -> 426508.38 | J10: =SUM(J2:J9) -> 141646.71

Sheet Furnizori
A1: Furnizor marfa | B1: Achizitii iulie | C1: Achizitii august | D1: Achizitii septembrie | E1: Total trimestru (fara TVA)
A2: Conex Distributie SRL | B2: =SUMIFS(Achizitii!$I:$I,Achizitii!$D:$D,$A2,Achizitii!$A:$A,"2026-07") -> 15160 | C2: =SUMIFS(Achizitii!$I:$I,Achizitii!$D:$D,$A2,Achizitii!$A:$A,"2026-08") -> 9620 | D2: =SUMIFS(Achizitii!$I:$I,Achizitii!$D:$D,$A2,Achizitii!$A:$A,"2026-09") -> 14435 | E2: =SUM(B2:D2) -> 39215
A3: DataStore Distributie SRL | B3: =SUMIFS(Achizitii!$I:$I,Achizitii!$D:$D,$A3,Achizitii!$A:$A,"2026-07") -> 17940 | C3: =SUMIFS(Achizitii!$I:$I,Achizitii!$D:$D,$A3,Achizitii!$A:$A,"2026-08") -> 12320 | D3: =SUMIFS(Achizitii!$I:$I,Achizitii!$D:$D,$A3,Achizitii!$A:$A,"2026-09") -> 12320 | E3: =SUM(B3:D3) -> 42580
A4: SoundLine Trading SRL | B4: =SUMIFS(Achizitii!$I:$I,Achizitii!$D:$D,$A4,Achizitii!$A:$A,"2026-07") -> 14300 | C4: =SUMIFS(Achizitii!$I:$I,Achizitii!$D:$D,$A4,Achizitii!$A:$A,"2026-08") -> 12600 | D4: =SUMIFS(Achizitii!$I:$I,Achizitii!$D:$D,$A4,Achizitii!$A:$A,"2026-09") -> 11700 | E4: =SUM(B4:D4) -> 38600
A5: TechSource Import SRL | B5: =SUMIFS(Achizitii!$I:$I,Achizitii!$D:$D,$A5,Achizitii!$A:$A,"2026-07") -> 45500 | C5: =SUMIFS(Achizitii!$I:$I,Achizitii!$D:$D,$A5,Achizitii!$A:$A,"2026-08") -> 24700 | D5: =SUMIFS(Achizitii!$I:$I,Achizitii!$D:$D,$A5,Achizitii!$A:$A,"2026-09") -> 42500 | E5: =SUM(B5:D5) -> 112700
A6: TOTAL | B6: =SUM(B2:B5) -> 92900 | C6: =SUM(C2:C5) -> 59240 | D6: =SUM(D2:D5) -> 80955 | E6: =SUM(E2:E5) -> 233095

Sheet TVA
A1: Decont TVA (estimativ) - T3 2026
A3: Indicator | B3: Iulie | C3: August | D3: Septembrie | E3: Total T3
A4: Baza impozabila livrari (vanzari fara TVA) | B4: =SUMIFS(Vanzari!$J:$J,Vanzari!$A:$A,"2026-07") -> 149435.57 | C4: =SUMIFS(Vanzari!$J:$J,Vanzari!$A:$A,"2026-08") -> 124418.19 | D4: =SUMIFS(Vanzari!$J:$J,Vanzari!$A:$A,"2026-09") -> 152654.62 | E4: =SUM(B4:D4) -> 426508.38
A5: TVA colectata | B5: =SUMIFS(Vanzari!$K:$K,Vanzari!$A:$A,"2026-07") -> 31381.54 | C5: =SUMIFS(Vanzari!$K:$K,Vanzari!$A:$A,"2026-08") -> 26127.91 | D5: =SUMIFS(Vanzari!$K:$K,Vanzari!$A:$A,"2026-09") -> 32057.56 | E5: =SUM(B5:D5) -> 89567.01
A6: TVA deductibila - achizitii marfa | B6: =SUMIFS(Achizitii!$J:$J,Achizitii!$A:$A,"2026-07") -> 19509 | C6: =SUMIFS(Achizitii!$J:$J,Achizitii!$A:$A,"2026-08") -> 12440.4 | D6: =SUMIFS(Achizitii!$J:$J,Achizitii!$A:$A,"2026-09") -> 17000.55 | E6: =SUM(B6:D6) -> 48949.95
A7: TVA deductibila - cheltuieli | B7: =SUMIFS(Cheltuieli!$H:$H,Cheltuieli!$A:$A,"2026-07") -> 2890.95 | C7: =SUMIFS(Cheltuieli!$H:$H,Cheltuieli!$A:$A,"2026-08") -> 3045.47 | D7: =SUMIFS(Cheltuieli!$H:$H,Cheltuieli!$A:$A,"2026-09") -> 2906.71 | E7: =SUM(B7:D7) -> 8843.13
A8: Total TVA deductibila | B8: =B6+B7 -> 22399.95 | C8: =C6+C7 -> 15485.87 | D8: =D6+D7 -> 19907.26 | E8: =SUM(B8:D8) -> 57793.08
A9: TVA de plata / (de recuperat) | B9: =B5-B8 -> 8981.59 | C9: =C5-C8 -> 10642.04 | D9: =D5-D8 -> 12150.3 | E9: =SUM(B9:D9) -> 31773.93
A11: Firma se presupune platitoare de TVA cu decont lunar (cifra de afaceri peste 100.000 EUR). Chiria se presupune cu TVA (proprietar care a optat pentru taxare).
